README.md
setup.py
fin_tools/__init__.py
fin_tools/utils.py
fin_tools/bin/__init__.py
fin_tools/bin/eaoi.py
fintools.egg-info/PKG-INFO
fintools.egg-info/SOURCES.txt
fintools.egg-info/dependency_links.txt
fintools.egg-info/entry_points.txt
fintools.egg-info/requires.txt
fintools.egg-info/top_level.txt
tests/__init__.py