Metadata-Version: 2.1
Name: fintools
Version: 0.1.1
Summary: Finance tools
Home-page: https://github.com/hotbaby/finance-tools
Author: Meng yangyang
Author-email: mengyy_linux@163.com
License: UNKNOWN
Platform: UNKNOWN
Classifier: Programming Language :: Python :: 2
Classifier: License :: OSI Approved :: MIT License
Classifier: Operating System :: OS Independent
